di/__init__.py
di/core/__init__.py
di/core/app.py
di/core/assignment/__init__.py
di/core/assignment/base.py
di/core/assignment/factories.py
di/core/assignment/mappers.py
di/core/assignment/matchers.py
di/core/assignment/selectors.py
di/core/compose/__init__.py
di/core/compose/base.py
di/core/compose/composers.py
di/core/element.py
di/core/injection/__init__.py
di/core/injection/base.py
di/core/injection/solvers.py
di/core/injectors.py
di/core/instance/__init__.py
di/core/instance/base.py
di/core/instance/recursive.py
di/core/module/__init__.py
di/core/module/base.py
di/core/module/solvers.py
di/core/navigator.py
di/core/provide_strategies.py
di/declarative/__init__.py
di/declarative/aggregation/__init__.py
di/declarative/aggregation/checks.py
di/declarative/aggregation/registry.py
di/declarative/aggregation/selector.py
di/declarative/app/__init__.py
di/declarative/app/app.py
di/declarative/app/globals.py
di/declarative/element/__init__.py
di/declarative/element/base.py
di/declarative/element/filters.py
di/declarative/element/iterables.py
di/declarative/module/__init__.py
di/declarative/module/assembly.py
di/declarative/module/imports.py
di/declarative/module/module.py
di/declarative/module/solvers.py
di/utils/__init__.py
di/utils/compat.py
di/utils/graph.py
di/utils/inspection/__init__.py
di/utils/inspection/abstract.py
di/utils/inspection/factory.py
di/utils/inspection/module_factories/__init__.py
di/utils/inspection/module_factories/base.py
di/utils/inspection/module_factories/filters.py
di/utils/inspection/module_factories/inspector.py
di/utils/inspection/module_variables/__init__.py
di/utils/inspection/module_variables/base.py
di/utils/inspection/module_variables/filters.py
di/utils/inspection/module_variables/inspector.py
di/utils/inspection/typing.py
python_di-1.1.1.dist-info/LICENSE
python_di-1.1.1.dist-info/WHEEL
python_di-1.1.1.dist-info/METADATA
python_di-1.1.1.dist-info/RECORD
